perceval/backends/zulip/__init__.py
perceval/backends/zulip/_version.py
perceval/backends/zulip/zulip.py
perceval_zulip-0.3.0.dist-info/LICENSE
perceval_zulip-0.3.0.dist-info/METADATA
perceval_zulip-0.3.0.dist-info/WHEEL
perceval_zulip-0.3.0.dist-info/RECORD
