Metadata-Version: 2.1
Name: perceval-zulip
Version: 0.3.0
Summary: Perceval backend for Zulip.
Home-page: https://chaoss.github.io/grimoirelab/
License: GPL-3.0+
Keywords: development,grimoirelab
Author: GrimoireLab Developers
Requires-Python: >=3.8,<4.0
Classifier: Development Status :: 4 - Beta
Classifier: Intended Audience :: Developers
Classifier: Intended Audience :: Science/Research
Classifier: License :: OSI Approved :: GNU General Public License v3 or later (GPLv3+)
Classifier: Programming Language :: Python :: 3
Classifier: Programming Language :: Python :: 3.8
Classifier: Programming Language :: Python :: 3.9
Classifier: Programming Language :: Python :: 3.10
Classifier: Programming Language :: Python :: 3.11
Classifier: Topic :: Software Development
Requires-Dist: grimoirelab-toolkit (>=0.3,<1.1)
Requires-Dist: perceval (>=1.0.2,<1.1)
Requires-Dist: requests (>=2.7,<3.0)
Project-URL: Bug Tracker, https://github.com/vchrombie/grimoirelab-perceval-zulip/issues
Project-URL: Repository, https://github.com/vchrombie/grimoirelab-perceval-zulip
